{"id": "043033", "bkmk": "kmtb-b043033", "name": "下鳥田町 発 特37号系統  北大路バスターミナル行き", "busstop": "下鳥田町", "line": "特37号系統", "destination": "北大路バスターミナル行き", "notes": {}, "weekday": [{"t": "07:00", "note": " "}, {"t": "07:50", "note": " "}, {"t": "08:56", "note": " "}, {"t": "09:54", "note": " "}, {"t": "10:54", "note": " "}, {"t": "12:24", "note": " "}, {"t": "13:54", "note": " "}, {"t": "15:24", "note": " "}, {"t": "16:54", "note": " "}, {"t": "17:54", "note": " "}, {"t": "18:54", "note": " "}, {"t": "20:15", "note": " "}, {"t": "21:45", "note": " "}], "saturday": [{"t": "07:00", "note": " "}, {"t": "07:50", "note": " "}, {"t": "08:56", "note": " "}, {"t": "09:54", "note": " "}, {"t": "10:54", "note": " "}, {"t": "12:24", "note": " "}, {"t": "13:54", "note": " "}, {"t": "15:24", "note": " "}, {"t": "16:54", "note": " "}, {"t": "17:54", "note": " "}, {"t": "18:54", "note": " "}, {"t": "20:15", "note": " "}, {"t": "21:45", "note": " "}], "holiday": [{"t": "07:00", "note": " "}, {"t": "07:50", "note": " "}, {"t": "08:56", "note": " "}, {"t": "09:54", "note": " "}, {"t": "10:54", "note": " "}, {"t": "12:24", "note": " "}, {"t": "13:54", "note": " "}, {"t": "15:24", "note": " "}, {"t": "16:54", "note": " "}, {"t": "17:54", "note": " "}, {"t": "18:54", "note": " "}, {"t": "20:15", "note": " "}, {"t": "21:45", "note": " "}]}