{"id": "058031", "bkmk": "kmtb-b058031", "name": "烏丸六条 発 5号系統  京都駅行き", "busstop": "烏丸六条", "line": "5号系統", "destination": "京都駅行き", "notes": {}, "weekday": [{"t": "06:41", "note": " "}, {"t": "06:54", "note": " "}, {"t": "07:06", "note": " "}, {"t": "07:16", "note": " "}, {"t": "07:25", "note": " "}, {"t": "07:34", "note": " "}, {"t": "07:48", "note": " "}, {"t": "07:56", "note": " "}, {"t": "08:05", "note": " "}, {"t": "08:14", "note": " "}, {"t": "08:24", "note": " "}, {"t": "08:31", "note": " "}, {"t": "08:41", "note": " "}, {"t": "08:47", "note": " "}, {"t": "08:57", "note": " "}, {"t": "09:05", "note": " "}, {"t": "09:17", "note": " "}, {"t": "09:25", "note": " "}, {"t": "09:37", "note": " "}, {"t": "09:45", "note": " "}, {"t": "09:57", "note": " "}, {"t": "10:05", "note": " "}, {"t": "10:18", "note": " "}, {"t": "10:25", "note": " "}, {"t": "10:38", "note": " "}, {"t": "10:45", "note": " "}, {"t": "10:58", "note": " "}, {"t": "11:05", "note": " "}, {"t": "11:18", "note": " "}, {"t": "11:25", "note": " "}, {"t": "11:38", "note": " "}, {"t": "11:45", "note": " "}, {"t": "11:58", "note": " "}, {"t": "12:05", "note": " "}, {"t": "12:18", "note": " "}, {"t": "12:25", "note": " "}, {"t": "12:38", "note": " "}, {"t": "12:45", "note": " "}, {"t": "12:58", "note": " "}, {"t": "13:05", "note": " "}, {"t": "13:18", "note": " "}, {"t": "13:25", "note": " "}, {"t": "13:38", "note": " "}, {"t": "13:45", "note": " "}, {"t": "13:58", "note": " "}, {"t": "14:05", "note": " "}, {"t": "14:18", "note": " "}, {"t": "14:25", "note": " "}, {"t": "14:38", "note": " "}, {"t": "14:45", "note": " "}, {"t": "14:56", "note": " "}, {"t": "15:00", "note": " "}, {"t": "15:08", "note": " "}, {"t": "15:18", "note": " "}, {"t": "15:23", "note": " "}, {"t": "15:33", "note": " "}, {"t": "15:38", "note": " "}, {"t": "15:48", "note": " "}, {"t": "15:53", "note": " "}, {"t": "16:03", "note": " "}, {"t": "16:08", "note": " "}, {"t": "16:18", "note": " "}, {"t": "16:23", "note": " "}, {"t": "16:33", "note": " "}, {"t": "16:38", "note": " "}, {"t": "16:48", "note": " "}, {"t": "16:53", "note": " "}, {"t": "17:03", "note": " "}, {"t": "17:08", "note": " "}, {"t": "17:18", "note": " "}, {"t": "17:23", "note": " "}, {"t": "17:33", "note": " "}, {"t": "17:38", "note": " "}, {"t": "17:48", "note": " "}, {"t": "17:53", "note": " "}, {"t": "18:03", "note": " "}, {"t": "18:08", "note": " "}, {"t": "18:18", "note": " "}, {"t": "18:23", "note": " "}, {"t": "18:33", "note": " "}, {"t": "18:38", "note": " "}, {"t": "18:48", "note": " "}, {"t": "18:54", "note": " "}, {"t": "19:06", "note": " "}, {"t": "19:13", "note": " "}, {"t": "19:24", "note": " "}, {"t": "19:34", "note": " "}, {"t": "19:45", "note": " "}, {"t": "19:55", "note": " "}, {"t": "20:10", "note": " "}, {"t": "20:18", "note": " "}, {"t": "20:30", "note": " "}, {"t": "20:48", "note": " "}, {"t": "21:10", "note": " "}, {"t": "21:28", "note": " "}, {"t": "21:49", "note": " "}, {"t": "22:07", "note": " "}, {"t": "22:29", "note": " "}, {"t": "22:47", "note": " "}, {"t": "23:09", "note": " "}], "saturday": [{"t": "06:41", "note": " "}, {"t": "06:57", "note": " "}, {"t": "07:16", "note": " "}, {"t": "07:32", "note": " "}, {"t": "07:48", "note": " "}, {"t": "07:59", "note": " "}, {"t": "08:12", "note": " "}, {"t": "08:23", "note": " "}, {"t": "08:38", "note": " "}, {"t": "08:51", "note": " "}, {"t": "09:07", "note": " "}, {"t": "09:21", "note": " "}, {"t": "09:35", "note": " "}, {"t": "09:45", "note": " "}, {"t": "09:57", "note": " "}, {"t": "10:05", "note": " "}, {"t": "10:18", "note": " "}, {"t": "10:25", "note": " "}, {"t": "10:38", "note": " "}, {"t": "10:45", "note": " "}, {"t": "10:58", "note": " "}, {"t": "11:05", "note": " "}, {"t": "11:18", "note": " "}, {"t": "11:25", "note": " "}, {"t": "11:38", "note": " "}, {"t": "11:45", "note": " "}, {"t": "11:58", "note": " "}, {"t": "12:05", "note": " "}, {"t": "12:18", "note": " "}, {"t": "12:25", "note": " "}, {"t": "12:38", "note": " "}, {"t": "12:45", "note": " "}, {"t": "12:58", "note": " "}, {"t": "13:05", "note": " "}, {"t": "13:18", "note": " "}, {"t": "13:25", "note": " "}, {"t": "13:38", "note": " "}, {"t": "13:45", "note": " "}, {"t": "13:58", "note": " "}, {"t": "14:05", "note": " "}, {"t": "14:18", "note": " "}, {"t": "14:25", "note": " "}, {"t": "14:38", "note": " "}, {"t": "14:45", "note": " "}, {"t": "14:56", "note": " "}, {"t": "15:00", "note": " "}, {"t": "15:08", "note": " "}, {"t": "15:18", "note": " "}, {"t": "15:23", "note": " "}, {"t": "15:33", "note": " "}, {"t": "15:38", "note": " "}, {"t": "15:48", "note": " "}, {"t": "15:53", "note": " "}, {"t": "16:03", "note": " "}, {"t": "16:08", "note": " "}, {"t": "16:18", "note": " "}, {"t": "16:23", "note": " "}, {"t": "16:33", "note": " "}, {"t": "16:38", "note": " "}, {"t": "16:48", "note": " "}, {"t": "16:53", "note": " "}, {"t": "17:03", "note": " "}, {"t": "17:08", "note": " "}, {"t": "17:18", "note": " "}, {"t": "17:23", "note": " "}, {"t": "17:33", "note": " "}, {"t": "17:38", "note": " "}, {"t": "17:48", "note": " "}, {"t": "17:53", "note": " "}, {"t": "18:03", "note": " "}, {"t": "18:08", "note": " "}, {"t": "18:18", "note": " "}, {"t": "18:23", "note": " "}, {"t": "18:33", "note": " "}, {"t": "18:38", "note": " "}, {"t": "18:48", "note": " "}, {"t": "18:54", "note": " "}, {"t": "19:06", "note": " "}, {"t": "19:13", "note": " "}, {"t": "19:24", "note": " "}, {"t": "19:34", "note": " "}, {"t": "19:45", "note": " "}, {"t": "19:55", "note": " "}, {"t": "20:10", "note": " "}, {"t": "20:18", "note": " "}, {"t": "20:30", "note": " "}, {"t": "20:48", "note": " "}, {"t": "21:10", "note": " "}, {"t": "21:28", "note": " "}, {"t": "21:49", "note": " "}, {"t": "22:07", "note": " "}, {"t": "22:29", "note": " "}, {"t": "22:47", "note": " "}, {"t": "23:09", "note": " "}], "holiday": [{"t": "06:41", "note": " "}, {"t": "06:57", "note": " "}, {"t": "07:16", "note": " "}, {"t": "07:32", "note": " "}, {"t": "07:48", "note": " "}, {"t": "07:59", "note": " "}, {"t": "08:12", "note": " "}, {"t": "08:23", "note": " "}, {"t": "08:38", "note": " "}, {"t": "08:51", "note": " "}, {"t": "09:07", "note": " "}, {"t": "09:21", "note": " "}, {"t": "09:35", "note": " "}, {"t": "09:45", "note": " "}, {"t": "09:57", "note": " "}, {"t": "10:05", "note": " "}, {"t": "10:18", "note": " "}, {"t": "10:25", "note": " "}, {"t": "10:38", "note": " "}, {"t": "10:45", "note": " "}, {"t": "10:58", "note": " "}, {"t": "11:05", "note": " "}, {"t": "11:18", "note": " "}, {"t": "11:25", "note": " "}, {"t": "11:38", "note": " "}, {"t": "11:45", "note": " "}, {"t": "11:58", "note": " "}, {"t": "12:05", "note": " "}, {"t": "12:18", "note": " "}, {"t": "12:25", "note": " "}, {"t": "12:38", "note": " "}, {"t": "12:45", "note": " "}, {"t": "12:58", "note": " "}, {"t": "13:05", "note": " "}, {"t": "13:18", "note": " "}, {"t": "13:25", "note": " "}, {"t": "13:38", "note": " "}, {"t": "13:45", "note": " "}, {"t": "13:58", "note": " "}, {"t": "14:05", "note": " "}, {"t": "14:18", "note": " "}, {"t": "14:25", "note": " "}, {"t": "14:38", "note": " "}, {"t": "14:45", "note": " "}, {"t": "14:56", "note": " "}, {"t": "15:00", "note": " "}, {"t": "15:08", "note": " "}, {"t": "15:18", "note": " "}, {"t": "15:23", "note": " "}, {"t": "15:33", "note": " "}, {"t": "15:38", "note": " "}, {"t": "15:48", "note": " "}, {"t": "15:53", "note": " "}, {"t": "16:03", "note": " "}, {"t": "16:08", "note": " "}, {"t": "16:18", "note": " "}, {"t": "16:23", "note": " "}, {"t": "16:33", "note": " "}, {"t": "16:38", "note": " "}, {"t": "16:48", "note": " "}, {"t": "16:53", "note": " "}, {"t": "17:03", "note": " "}, {"t": "17:08", "note": " "}, {"t": "17:18", "note": " "}, {"t": "17:23", "note": " "}, {"t": "17:33", "note": " "}, {"t": "17:38", "note": " "}, {"t": "17:48", "note": " "}, {"t": "17:53", "note": " "}, {"t": "18:03", "note": " "}, {"t": "18:08", "note": " "}, {"t": "18:18", "note": " "}, {"t": "18:23", "note": " "}, {"t": "18:33", "note": " "}, {"t": "18:38", "note": " "}, {"t": "18:48", "note": " "}, {"t": "18:54", "note": " "}, {"t": "19:06", "note": " "}, {"t": "19:13", "note": " "}, {"t": "19:24", "note": " "}, {"t": "19:34", "note": " "}, {"t": "19:45", "note": " "}, {"t": "19:55", "note": " "}, {"t": "20:10", "note": " "}, {"t": "20:18", "note": " "}, {"t": "20:30", "note": " "}, {"t": "20:48", "note": " "}, {"t": "21:10", "note": " "}, {"t": "21:28", "note": " "}, {"t": "21:49", "note": " "}, {"t": "22:07", "note": " "}, {"t": "22:29", "note": " "}, {"t": "22:47", "note": " "}, {"t": "23:09", "note": " "}]}