{"id": "092013", "bkmk": "kmtb-b092013", "name": "岩倉大鷺町 発 65号系統 熊野神社　烏丸丸太町 四条烏丸行き", "busstop": "岩倉大鷺町", "line": "65号系統", "destination": "四条烏丸行き", "notes": {}, "weekday": [{"t": "06:41", "note": " "}, {"t": "07:23", "note": " "}, {"t": "08:01", "note": " "}, {"t": "08:41", "note": " "}, {"t": "09:21", "note": " "}, {"t": "10:21", "note": " "}, {"t": "11:21", "note": " "}, {"t": "12:21", "note": " "}, {"t": "13:21", "note": " "}, {"t": "14:21", "note": " "}, {"t": "15:11", "note": " "}, {"t": "16:01", "note": " "}, {"t": "16:51", "note": " "}, {"t": "17:41", "note": " "}, {"t": "18:26", "note": " "}, {"t": "19:11", "note": " "}, {"t": "19:58", "note": " "}, {"t": "21:18", "note": " "}], "saturday": [{"t": "07:16", "note": " "}, {"t": "08:21", "note": " "}, {"t": "09:21", "note": " "}, {"t": "10:21", "note": " "}, {"t": "11:21", "note": " "}, {"t": "12:21", "note": " "}, {"t": "13:21", "note": " "}, {"t": "14:21", "note": " "}, {"t": "15:21", "note": " "}, {"t": "16:21", "note": " "}, {"t": "17:21", "note": " "}, {"t": "18:21", "note": " "}, {"t": "19:26", "note": " "}, {"t": "20:26", "note": " "}], "holiday": [{"t": "07:16", "note": " "}, {"t": "09:21", "note": " "}, {"t": "10:21", "note": " "}, {"t": "11:21", "note": " "}, {"t": "12:21", "note": " "}, {"t": "13:21", "note": " "}, {"t": "14:21", "note": " "}, {"t": "15:21", "note": " "}, {"t": "16:21", "note": " "}, {"t": "17:21", "note": " "}, {"t": "18:21", "note": " "}, {"t": "20:26", "note": " "}]}