{"id": "275031", "bkmk": "kmtb-b275031", "name": "藤ノ森 発 南8号系統 御香宮　桃陵団地 中書島･横大路車庫行き", "busstop": "藤ノ森", "line": "南8号系統", "destination": "中書島･横大路車庫行き", "notes": {".": "京阪中書島・伏見港公園には停まりません。"}, "weekday": [{"t": "07:05", "note": " "}, {"t": "07:55", "note": " "}, {"t": "08:25", "note": " "}, {"t": "09:25", "note": " "}, {"t": "10:00", "note": " "}, {"t": "10:45", "note": " "}, {"t": "11:30", "note": " "}, {"t": "12:15", "note": " "}, {"t": "13:00", "note": " "}, {"t": "13:45", "note": " "}, {"t": "14:30", "note": " "}, {"t": "15:15", "note": " "}, {"t": "16:00", "note": " "}, {"t": "16:45", "note": " "}, {"t": "17:30", "note": " "}, {"t": "18:15", "note": " "}, {"t": "19:00", "note": " "}, {"t": "19:40", "note": " "}, {"t": "20:20", "note": " "}, {"t": "20:55", "note": " "}, {"t": "21:35", "note": " "}], "saturday": [{"t": "07:10", "note": " "}, {"t": "08:10", "note": " "}, {"t": "09:00", "note": " "}, {"t": "10:00", "note": " "}, {"t": "10:45", "note": " "}, {"t": "11:30", "note": " "}, {"t": "12:15", "note": " "}, {"t": "13:00", "note": " "}, {"t": "13:45", "note": " "}, {"t": "14:30", "note": " "}, {"t": "15:15", "note": " "}, {"t": "16:00", "note": " "}, {"t": "16:45", "note": " "}, {"t": "17:30", "note": " "}, {"t": "18:15", "note": " "}, {"t": "19:00", "note": " "}, {"t": "19:40", "note": " "}, {"t": "20:20", "note": " "}, {"t": "21:25", "note": " "}], "holiday": [{"t": "07:10", "note": " "}, {"t": "08:10", "note": " "}, {"t": "09:00", "note": " "}, {"t": "10:00", "note": " "}, {"t": "10:45", "note": " "}, {"t": "11:30", "note": " "}, {"t": "12:15", "note": " "}, {"t": "13:00", "note": " "}, {"t": "13:45", "note": " "}, {"t": "14:30", "note": " "}, {"t": "15:15", "note": " "}, {"t": "16:00", "note": " "}, {"t": "16:45", "note": " "}, {"t": "17:30", "note": " "}, {"t": "18:15", "note": " "}, {"t": "19:00", "note": " "}, {"t": "19:40", "note": " "}, {"t": "20:20", "note": " "}, {"t": "21:25", "note": " "}]}