{"id": "301044", "bkmk": "kmtb-b301044", "name": "島原口 発 58号系統  四条大宮･二条駅行き", "busstop": "島原口", "line": "58号系統", "destination": "四条大宮･二条駅行き", "notes": {}, "weekday": [], "saturday": [{"t": "10:39", "note": " "}, {"t": "11:09", "note": " "}, {"t": "11:39", "note": " "}, {"t": "12:09", "note": " "}, {"t": "12:39", "note": " "}, {"t": "13:09", "note": " "}, {"t": "13:39", "note": " "}, {"t": "14:09", "note": " "}, {"t": "14:39", "note": " "}, {"t": "15:09", "note": " "}, {"t": "15:39", "note": " "}, {"t": "16:09", "note": " "}, {"t": "16:39", "note": " "}, {"t": "17:09", "note": " "}], "holiday": [{"t": "10:39", "note": " "}, {"t": "11:09", "note": " "}, {"t": "11:39", "note": " "}, {"t": "12:09", "note": " "}, {"t": "12:39", "note": " "}, {"t": "13:09", "note": " "}, {"t": "13:39", "note": " "}, {"t": "14:09", "note": " "}, {"t": "14:39", "note": " "}, {"t": "15:09", "note": " "}, {"t": "15:39", "note": " "}, {"t": "16:09", "note": " "}, {"t": "16:39", "note": " "}, {"t": "17:09", "note": " "}]}