{"id": "309021", "bkmk": "kmtb-b309021", "name": "上鳥羽 発 84号系統 葛野大路通 太秦天神川駅行き", "busstop": "上鳥羽", "line": "84号系統", "destination": "太秦天神川駅行き", "notes": {"*": "以外は小型バス車両で運行いたします。"}, "weekday": [{"t": "06:47", "note": " "}, {"t": "07:24", "note": "以外は小型バス車両で運行いたします。"}, {"t": "07:54", "note": "以外は小型バス車両で運行いたします。"}, {"t": "08:44", "note": " "}, {"t": "09:29", "note": " "}, {"t": "10:09", "note": " "}, {"t": "10:54", "note": " "}, {"t": "11:39", "note": " "}, {"t": "12:24", "note": " "}, {"t": "13:09", "note": " "}, {"t": "13:54", "note": " "}, {"t": "14:39", "note": " "}, {"t": "15:19", "note": " "}, {"t": "15:59", "note": " "}, {"t": "16:39", "note": " "}, {"t": "17:19", "note": " "}, {"t": "17:59", "note": "以外は小型バス車両で運行いたします。"}, {"t": "18:39", "note": "以外は小型バス車両で運行いたします。"}, {"t": "19:17", "note": " "}, {"t": "20:07", "note": " "}, {"t": "21:07", "note": " "}, {"t": "21:56", "note": " "}], "saturday": [{"t": "06:47", "note": " "}, {"t": "07:30", "note": " "}, {"t": "08:00", "note": " "}, {"t": "08:40", "note": " "}, {"t": "09:41", "note": " "}, {"t": "10:41", "note": " "}, {"t": "11:41", "note": " "}, {"t": "12:41", "note": " "}, {"t": "13:41", "note": " "}, {"t": "14:41", "note": " "}, {"t": "15:41", "note": " "}, {"t": "16:41", "note": " "}, {"t": "17:41", "note": " "}, {"t": "18:41", "note": " "}, {"t": "19:40", "note": " "}, {"t": "20:47", "note": " "}, {"t": "21:56", "note": " "}], "holiday": [{"t": "07:37", "note": " "}, {"t": "08:40", "note": " "}, {"t": "09:41", "note": " "}, {"t": "10:41", "note": " "}, {"t": "11:41", "note": " "}, {"t": "12:41", "note": " "}, {"t": "13:41", "note": " "}, {"t": "14:41", "note": " "}, {"t": "15:41", "note": " "}, {"t": "16:41", "note": " "}, {"t": "17:41", "note": " "}, {"t": "18:41", "note": " "}, {"t": "19:40", "note": " "}, {"t": "20:47", "note": " "}, {"t": "21:56", "note": " "}]}