{"id": "396043", "bkmk": "kmtb-b396043", "name": "千本上立売 発 59号系統  金閣寺･竜安寺・山越行き", "busstop": "千本上立売", "line": "59号系統", "destination": "金閣寺･竜安寺・山越行き", "notes": {"()": "広沢池・佛大広沢校前経由山越中町行きです。"}, "weekday": [{"t": "07:06", "note": " "}, {"t": "07:26", "note": " "}, {"t": "07:44", "note": " "}, {"t": "08:02", "note": " "}, {"t": "08:20", "note": " "}, {"t": "08:39", "note": "広沢池・佛大広沢校前経由山越中町行きです。"}, {"t": "08:56", "note": " "}, {"t": "09:11", "note": " "}, {"t": "09:26", "note": " "}, {"t": "09:41", "note": "広沢池・佛大広沢校前経由山越中町行きです。"}, {"t": "09:56", "note": " "}, {"t": "10:11", "note": " "}, {"t": "10:26", "note": " "}, {"t": "10:41", "note": "広沢池・佛大広沢校前経由山越中町行きです。"}, {"t": "10:56", "note": " "}, {"t": "11:11", "note": " "}, {"t": "11:26", "note": " "}, {"t": "11:41", "note": "広沢池・佛大広沢校前経由山越中町行きです。"}, {"t": "11:56", "note": " "}, {"t": "12:11", "note": " "}, {"t": "12:26", "note": " "}, {"t": "12:41", "note": "広沢池・佛大広沢校前経由山越中町行きです。"}, {"t": "12:56", "note": " "}, {"t": "13:11", "note": " "}, {"t": "13:26", "note": " "}, {"t": "13:38", "note": " "}, {"t": "13:50", "note": "広沢池・佛大広沢校前経由山越中町行きです。"}, {"t": "14:02", "note": " "}, {"t": "14:14", "note": " "}, {"t": "14:26", "note": " "}, {"t": "14:38", "note": " "}, {"t": "14:50", "note": " "}, {"t": "15:02", "note": "広沢池・佛大広沢校前経由山越中町行きです。"}, {"t": "15:14", "note": " "}, {"t": "15:26", "note": " "}, {"t": "15:38", "note": " "}, {"t": "15:50", "note": "広沢池・佛大広沢校前経由山越中町行きです。"}, {"t": "16:02", "note": " "}, {"t": "16:14", "note": " "}, {"t": "16:26", "note": " "}, {"t": "16:38", "note": " "}, {"t": "16:50", "note": " "}, {"t": "17:02", "note": " "}, {"t": "17:14", "note": " "}, {"t": "17:26", "note": " "}, {"t": "17:41", "note": " "}, {"t": "17:56", "note": " "}, {"t": "18:11", "note": " "}, {"t": "18:26", "note": " "}, {"t": "18:41", "note": " "}, {"t": "18:56", "note": " "}, {"t": "19:10", "note": " "}, {"t": "19:23", "note": " "}, {"t": "19:37", "note": " "}, {"t": "19:50", "note": " "}, {"t": "20:02", "note": " "}, {"t": "20:16", "note": " "}, {"t": "20:36", "note": " "}, {"t": "20:56", "note": " "}, {"t": "21:15", "note": " "}, {"t": "21:34", "note": " "}, {"t": "22:02", "note": " "}], "saturday": [{"t": "07:06", "note": " "}, {"t": "07:26", "note": " "}, {"t": "07:49", "note": " "}, {"t": "08:11", "note": " "}, {"t": "08:31", "note": "広沢池・佛大広沢校前経由山越中町行きです。"}, {"t": "08:56", "note": " "}, {"t": "09:19", "note": " "}, {"t": "09:46", "note": "広沢池・佛大広沢校前経由山越中町行きです。"}, {"t": "10:06", "note": " "}, {"t": "10:26", "note": " "}, {"t": "10:41", "note": "広沢池・佛大広沢校前経由山越中町行きです。"}, {"t": "10:56", "note": " "}, {"t": "11:11", "note": " "}, {"t": "11:26", "note": " "}, {"t": "11:41", "note": "広沢池・佛大広沢校前経由山越中町行きです。"}, {"t": "11:56", "note": " "}, {"t": "12:11", "note": " "}, {"t": "12:26", "note": " "}, {"t": "12:41", "note": "広沢池・佛大広沢校前経由山越中町行きです。"}, {"t": "12:56", "note": " "}, {"t": "13:11", "note": " "}, {"t": "13:26", "note": " "}, {"t": "13:38", "note": " "}, {"t": "13:50", "note": "広沢池・佛大広沢校前経由山越中町行きです。"}, {"t": "14:02", "note": " "}, {"t": "14:14", "note": " "}, {"t": "14:26", "note": " "}, {"t": "14:38", "note": " "}, {"t": "14:50", "note": "広沢池・佛大広沢校前経由山越中町行きです。"}, {"t": "15:02", "note": " "}, {"t": "15:14", "note": " "}, {"t": "15:26", "note": " "}, {"t": "15:38", "note": " "}, {"t": "15:50", "note": "広沢池・佛大広沢校前経由山越中町行きです。"}, {"t": "16:02", "note": " "}, {"t": "16:14", "note": " "}, {"t": "16:26", "note": " "}, {"t": "16:38", "note": " "}, {"t": "16:50", "note": " "}, {"t": "17:02", "note": " "}, {"t": "17:14", "note": " "}, {"t": "17:26", "note": " "}, {"t": "17:41", "note": " "}, {"t": "17:56", "note": " "}, {"t": "18:11", "note": " "}, {"t": "18:26", "note": " "}, {"t": "18:41", "note": " "}, {"t": "18:56", "note": " "}, {"t": "19:10", "note": " "}, {"t": "19:23", "note": " "}, {"t": "19:41", "note": " "}, {"t": "20:06", "note": " "}, {"t": "20:36", "note": " "}, {"t": "21:06", "note": " "}, {"t": "21:34", "note": " "}, {"t": "22:02", "note": " "}], "holiday": [{"t": "07:06", "note": " "}, {"t": "07:26", "note": " "}, {"t": "07:49", "note": " "}, {"t": "08:11", "note": " "}, {"t": "08:31", "note": "広沢池・佛大広沢校前経由山越中町行きです。"}, {"t": "08:56", "note": " "}, {"t": "09:19", "note": " "}, {"t": "09:46", "note": "広沢池・佛大広沢校前経由山越中町行きです。"}, {"t": "10:06", "note": " "}, {"t": "10:26", "note": " "}, {"t": "10:41", "note": "広沢池・佛大広沢校前経由山越中町行きです。"}, {"t": "10:56", "note": " "}, {"t": "11:11", "note": " "}, {"t": "11:26", "note": " "}, {"t": "11:41", "note": "広沢池・佛大広沢校前経由山越中町行きです。"}, {"t": "11:56", "note": " "}, {"t": "12:11", "note": " "}, {"t": "12:26", "note": " "}, {"t": "12:41", "note": "広沢池・佛大広沢校前経由山越中町行きです。"}, {"t": "12:56", "note": " "}, {"t": "13:11", "note": " "}, {"t": "13:26", "note": " "}, {"t": "13:38", "note": " "}, {"t": "13:50", "note": "広沢池・佛大広沢校前経由山越中町行きです。"}, {"t": "14:02", "note": " "}, {"t": "14:14", "note": " "}, {"t": "14:26", "note": " "}, {"t": "14:38", "note": " "}, {"t": "14:50", "note": "広沢池・佛大広沢校前経由山越中町行きです。"}, {"t": "15:02", "note": " "}, {"t": "15:14", "note": " "}, {"t": "15:26", "note": " "}, {"t": "15:38", "note": " "}, {"t": "15:50", "note": "広沢池・佛大広沢校前経由山越中町行きです。"}, {"t": "16:02", "note": " "}, {"t": "16:14", "note": " "}, {"t": "16:26", "note": " "}, {"t": "16:38", "note": " "}, {"t": "16:50", "note": " "}, {"t": "17:02", "note": " "}, {"t": "17:14", "note": " "}, {"t": "17:26", "note": " "}, {"t": "17:41", "note": " "}, {"t": "17:56", "note": " "}, {"t": "18:11", "note": " "}, {"t": "18:26", "note": " "}, {"t": "18:41", "note": " "}, {"t": "18:56", "note": " "}, {"t": "19:10", "note": " "}, {"t": "19:23", "note": " "}, {"t": "19:41", "note": " "}, {"t": "20:06", "note": " "}, {"t": "20:36", "note": " "}, {"t": "21:06", "note": " "}, {"t": "21:34", "note": " "}, {"t": "22:02", "note": " "}]}