{"id": "425021", "bkmk": "kmtb-b425021", "name": "嵯峨小学校前 発 11号系統  四条河原町・三条京阪行き", "busstop": "嵯峨小学校前", "line": "11号系統", "destination": "四条河原町・三条京阪行き", "notes": {".": "当バス停は休止します。嵯峨瀬戸川町西行バス停をご利用下さい。"}, "weekday": [{"t": "06:03", "note": " "}, {"t": "06:28", "note": " "}, {"t": "06:48", "note": " "}, {"t": "07:03", "note": " "}, {"t": "07:18", "note": " "}, {"t": "07:33", "note": " "}, {"t": "07:49", "note": " "}, {"t": "08:04", "note": " "}, {"t": "08:19", "note": " "}, {"t": "08:39", "note": " "}, {"t": "08:59", "note": " "}, {"t": "09:19", "note": " "}, {"t": "09:39", "note": " "}, {"t": "09:59", "note": " "}, {"t": "10:19", "note": " "}, {"t": "10:39", "note": " "}, {"t": "10:59", "note": " "}, {"t": "11:19", "note": " "}, {"t": "11:39", "note": " "}, {"t": "11:59", "note": " "}, {"t": "12:19", "note": " "}, {"t": "12:39", "note": " "}, {"t": "12:59", "note": " "}, {"t": "13:19", "note": " "}, {"t": "13:39", "note": " "}, {"t": "13:59", "note": " "}, {"t": "14:19", "note": " "}, {"t": "14:39", "note": " "}, {"t": "14:59", "note": " "}, {"t": "15:19", "note": " "}, {"t": "15:39", "note": " "}, {"t": "15:59", "note": " "}, {"t": "16:19", "note": " "}, {"t": "16:39", "note": " "}, {"t": "16:59", "note": " "}, {"t": "17:19", "note": " "}, {"t": "17:39", "note": " "}, {"t": "17:59", "note": " "}, {"t": "18:19", "note": " "}, {"t": "18:39", "note": " "}, {"t": "18:59", "note": " "}, {"t": "19:18", "note": " "}, {"t": "19:48", "note": " "}, {"t": "20:18", "note": " "}, {"t": "20:53", "note": " "}, {"t": "21:34", "note": " "}], "saturday": [], "holiday": []}