{"id": "672031", "bkmk": "kmtb-b672031", "name": "南春日町 発 臨西2号系統 西竹の里町 洛西バスターミナル行き", "busstop": "南春日町", "line": "臨西2号系統", "destination": "洛西バスターミナル行き", "notes": {}, "weekday": [{"t": "09:19", "note": " "}, {"t": "10:43", "note": " "}, {"t": "12:07", "note": " "}, {"t": "13:31", "note": " "}, {"t": "14:55", "note": " "}, {"t": "16:19", "note": " "}, {"t": "17:49", "note": " "}, {"t": "19:23", "note": " "}, {"t": "20:56", "note": " "}], "saturday": [{"t": "09:19", "note": " "}, {"t": "10:43", "note": " "}, {"t": "12:07", "note": " "}, {"t": "13:31", "note": " "}, {"t": "14:55", "note": " "}, {"t": "16:19", "note": " "}, {"t": "18:23", "note": " "}, {"t": "20:21", "note": " "}], "holiday": [{"t": "09:31", "note": " "}, {"t": "10:43", "note": " "}, {"t": "12:07", "note": " "}, {"t": "13:31", "note": " "}, {"t": "14:55", "note": " "}, {"t": "16:19", "note": " "}, {"t": "18:18", "note": " "}, {"t": "20:16", "note": " "}]}