{"id": "684031", "bkmk": "kmtb-b684031", "name": "月見ケ丘 発 69号系統 物集女　JR桂川駅 桂駅東口行き", "busstop": "月見ケ丘", "line": "69号系統", "destination": "桂駅東口行き", "notes": {}, "weekday": [{"t": "06:22", "note": " "}, {"t": "06:42", "note": " "}, {"t": "07:14", "note": " "}, {"t": "07:45", "note": " "}, {"t": "08:19", "note": " "}, {"t": "08:59", "note": " "}, {"t": "09:39", "note": " "}, {"t": "10:19", "note": " "}, {"t": "10:59", "note": " "}, {"t": "11:39", "note": " "}, {"t": "12:19", "note": " "}, {"t": "12:59", "note": " "}, {"t": "13:39", "note": " "}, {"t": "14:19", "note": " "}, {"t": "14:59", "note": " "}, {"t": "15:39", "note": " "}, {"t": "16:19", "note": " "}, {"t": "16:49", "note": " "}, {"t": "17:19", "note": " "}, {"t": "17:49", "note": " "}, {"t": "18:19", "note": " "}, {"t": "18:59", "note": " "}, {"t": "19:53", "note": " "}, {"t": "20:53", "note": " "}, {"t": "21:52", "note": " "}], "saturday": [{"t": "06:54", "note": " "}, {"t": "07:24", "note": " "}, {"t": "07:59", "note": " "}, {"t": "08:58", "note": " "}, {"t": "09:39", "note": " "}, {"t": "10:19", "note": " "}, {"t": "10:59", "note": " "}, {"t": "11:39", "note": " "}, {"t": "12:19", "note": " "}, {"t": "12:59", "note": " "}, {"t": "13:39", "note": " "}, {"t": "14:19", "note": " "}, {"t": "14:59", "note": " "}, {"t": "15:39", "note": " "}, {"t": "16:19", "note": " "}, {"t": "16:49", "note": " "}, {"t": "17:19", "note": " "}, {"t": "17:49", "note": " "}, {"t": "18:19", "note": " "}, {"t": "18:59", "note": " "}, {"t": "19:53", "note": " "}, {"t": "20:53", "note": " "}, {"t": "21:52", "note": " "}], "holiday": [{"t": "06:54", "note": " "}, {"t": "07:24", "note": " "}, {"t": "07:59", "note": " "}, {"t": "08:58", "note": " "}, {"t": "09:39", "note": " "}, {"t": "10:19", "note": " "}, {"t": "10:59", "note": " "}, {"t": "11:39", "note": " "}, {"t": "12:19", "note": " "}, {"t": "12:59", "note": " "}, {"t": "13:39", "note": " "}, {"t": "14:19", "note": " "}, {"t": "14:59", "note": " "}, {"t": "15:39", "note": " "}, {"t": "16:19", "note": " "}, {"t": "16:49", "note": " "}, {"t": "17:19", "note": " "}, {"t": "17:49", "note": " "}, {"t": "18:19", "note": " "}, {"t": "18:59", "note": " "}, {"t": "19:53", "note": " "}, {"t": "20:53", "note": " "}, {"t": "21:52", "note": " "}]}