{"id": "708011", "bkmk": "kmtb-b708011", "name": "上賀茂橋 発 4号系統  四条河原町・京都駅行き", "busstop": "上賀茂橋", "line": "4号系統", "destination": "四条河原町・京都駅行き", "notes": {".": "（　）印は，上賀茂小学校・松ヶ崎駅・左京区総合庁舎経由です。Via Matsugasaki Sta."}, "weekday": [{"t": "06:24", "note": " "}, {"t": "06:38", "note": " "}, {"t": "06:48", "note": "()"}, {"t": "07:04", "note": " "}, {"t": "07:14", "note": "()"}, {"t": "07:29", "note": " "}, {"t": "07:41", "note": "()"}, {"t": "07:59", "note": " "}, {"t": "08:11", "note": "()"}, {"t": "08:29", "note": " "}, {"t": "08:41", "note": "()"}, {"t": "08:59", "note": " "}, {"t": "09:11", "note": "()"}, {"t": "09:29", "note": " "}, {"t": "09:41", "note": "()"}, {"t": "09:59", "note": " "}, {"t": "10:11", "note": "()"}, {"t": "10:29", "note": " "}, {"t": "10:41", "note": "()"}, {"t": "10:59", "note": " "}, {"t": "11:11", "note": "()"}, {"t": "11:29", "note": " "}, {"t": "11:41", "note": "()"}, {"t": "11:59", "note": " "}, {"t": "12:11", "note": "()"}, {"t": "12:29", "note": " "}, {"t": "12:41", "note": "()"}, {"t": "12:59", "note": " "}, {"t": "13:11", "note": "()"}, {"t": "13:29", "note": " "}, {"t": "13:41", "note": "()"}, {"t": "13:59", "note": " "}, {"t": "14:11", "note": "()"}, {"t": "14:29", "note": " "}, {"t": "14:41", "note": "()"}, {"t": "14:59", "note": " "}, {"t": "15:11", "note": "()"}, {"t": "15:29", "note": " "}, {"t": "15:41", "note": "()"}, {"t": "15:59", "note": " "}, {"t": "16:11", "note": "()"}, {"t": "16:29", "note": " "}, {"t": "16:41", "note": "()"}, {"t": "16:59", "note": " "}, {"t": "17:11", "note": "()"}, {"t": "17:29", "note": " "}, {"t": "17:41", "note": "()"}, {"t": "17:59", "note": " "}, {"t": "18:11", "note": "()"}, {"t": "18:29", "note": " "}, {"t": "18:43", "note": "()"}, {"t": "19:01", "note": "()"}, {"t": "19:19", "note": " "}, {"t": "19:34", "note": "()"}, {"t": "19:57", "note": " "}, {"t": "20:14", "note": "()"}, {"t": "20:37", "note": " "}, {"t": "20:54", "note": "()"}, {"t": "21:17", "note": " "}], "saturday": [{"t": "06:24", "note": " "}, {"t": "06:46", "note": "()"}, {"t": "07:13", "note": " "}, {"t": "07:33", "note": "()"}, {"t": "07:57", "note": " "}, {"t": "08:12", "note": "()"}, {"t": "08:33", "note": " "}, {"t": "08:50", "note": "()"}, {"t": "09:13", "note": " "}, {"t": "09:31", "note": "()"}, {"t": "09:54", "note": " "}, {"t": "10:11", "note": "()"}, {"t": "10:29", "note": " "}, {"t": "10:41", "note": "()"}, {"t": "10:59", "note": " "}, {"t": "11:11", "note": "()"}, {"t": "11:29", "note": " "}, {"t": "11:41", "note": "()"}, {"t": "11:59", "note": " "}, {"t": "12:11", "note": "()"}, {"t": "12:29", "note": " "}, {"t": "12:41", "note": "()"}, {"t": "12:59", "note": " "}, {"t": "13:11", "note": "()"}, {"t": "13:29", "note": " "}, {"t": "13:41", "note": "()"}, {"t": "13:59", "note": " "}, {"t": "14:11", "note": "()"}, {"t": "14:29", "note": " "}, {"t": "14:41", "note": "()"}, {"t": "14:59", "note": " "}, {"t": "15:11", "note": "()"}, {"t": "15:29", "note": " "}, {"t": "15:41", "note": "()"}, {"t": "15:59", "note": " "}, {"t": "16:11", "note": "()"}, {"t": "16:32", "note": " "}, {"t": "16:49", "note": "()"}, {"t": "17:12", "note": " "}, {"t": "17:29", "note": "()"}, {"t": "17:52", "note": " "}, {"t": "18:09", "note": "()"}, {"t": "18:32", "note": " "}, {"t": "18:53", "note": "()"}, {"t": "19:17", "note": " "}, {"t": "19:34", "note": "()"}, {"t": "19:57", "note": " "}, {"t": "20:14", "note": "()"}, {"t": "20:37", "note": " "}, {"t": "20:54", "note": "()"}, {"t": "21:17", "note": " "}], "holiday": [{"t": "06:24", "note": " "}, {"t": "06:46", "note": "()"}, {"t": "07:13", "note": " "}, {"t": "07:33", "note": "()"}, {"t": "07:57", "note": " "}, {"t": "08:12", "note": "()"}, {"t": "08:33", "note": " "}, {"t": "08:50", "note": "()"}, {"t": "09:13", "note": " "}, {"t": "09:31", "note": "()"}, {"t": "09:54", "note": " "}, {"t": "10:11", "note": "()"}, {"t": "10:29", "note": " "}, {"t": "10:41", "note": "()"}, {"t": "10:59", "note": " "}, {"t": "11:11", "note": "()"}, {"t": "11:29", "note": " "}, {"t": "11:41", "note": "()"}, {"t": "11:59", "note": " "}, {"t": "12:11", "note": "()"}, {"t": "12:29", "note": " "}, {"t": "12:41", "note": "()"}, {"t": "12:59", "note": " "}, {"t": "13:11", "note": "()"}, {"t": "13:29", "note": " "}, {"t": "13:41", "note": "()"}, {"t": "13:59", "note": " "}, {"t": "14:11", "note": "()"}, {"t": "14:29", "note": " "}, {"t": "14:41", "note": "()"}, {"t": "14:59", "note": " "}, {"t": "15:11", "note": "()"}, {"t": "15:29", "note": " "}, {"t": "15:41", "note": "()"}, {"t": "15:59", "note": " "}, {"t": "16:11", "note": "()"}, {"t": "16:32", "note": " "}, {"t": "16:49", "note": "()"}, {"t": "17:12", "note": " "}, {"t": "17:29", "note": "()"}, {"t": "17:52", "note": " "}, {"t": "18:09", "note": "()"}, {"t": "18:32", "note": " "}, {"t": "18:53", "note": "()"}, {"t": "19:17", "note": " "}, {"t": "19:34", "note": "()"}, {"t": "19:57", "note": " "}, {"t": "20:14", "note": "()"}, {"t": "20:37", "note": " "}, {"t": "20:54", "note": "()"}, {"t": "21:17", "note": " "}]}