{"id": "791032", "bkmk": "kmtb-b791032", "name": "境谷センター前 発 西2号系統 西竹の里町 洛西バスターミナル行き", "busstop": "境谷センター前", "line": "西2号系統", "destination": "洛西バスターミナル行き", "notes": {"*": "右京の里経由です。"}, "weekday": [{"t": "06:34", "note": " "}, {"t": "06:49", "note": " "}, {"t": "06:59", "note": " "}, {"t": "07:09", "note": " "}, {"t": "07:19", "note": " "}, {"t": "07:28", "note": " "}, {"t": "07:38", "note": " "}, {"t": "07:46", "note": " "}, {"t": "07:53", "note": " "}, {"t": "07:58", "note": " "}, {"t": "08:05", "note": " "}, {"t": "08:11", "note": " "}, {"t": "08:17", "note": " "}, {"t": "08:24", "note": " "}, {"t": "08:31", "note": " "}, {"t": "08:39", "note": " "}, {"t": "08:49", "note": " "}, {"t": "09:00", "note": " "}, {"t": "09:24", "note": " "}, {"t": "09:36", "note": " "}, {"t": "09:48", "note": " "}, {"t": "10:00", "note": "右京の里経由です。"}, {"t": "10:12", "note": " "}, {"t": "10:24", "note": " "}, {"t": "10:48", "note": " "}, {"t": "11:00", "note": " "}, {"t": "11:12", "note": " "}, {"t": "11:24", "note": "右京の里経由です。"}, {"t": "11:36", "note": " "}, {"t": "11:48", "note": " "}, {"t": "12:12", "note": " "}, {"t": "12:24", "note": " "}, {"t": "12:36", "note": " "}, {"t": "12:48", "note": "右京の里経由です。"}, {"t": "13:00", "note": " "}, {"t": "13:12", "note": " "}, {"t": "13:36", "note": " "}, {"t": "13:48", "note": " "}, {"t": "14:00", "note": " "}, {"t": "14:12", "note": "右京の里経由です。"}, {"t": "14:24", "note": " "}, {"t": "14:36", "note": " "}, {"t": "15:00", "note": " "}, {"t": "15:12", "note": " "}, {"t": "15:24", "note": " "}, {"t": "15:36", "note": "右京の里経由です。"}, {"t": "15:48", "note": " "}, {"t": "16:00", "note": " "}, {"t": "16:24", "note": " "}, {"t": "16:36", "note": "右京の里経由です。"}, {"t": "16:48", "note": " "}, {"t": "17:00", "note": " "}, {"t": "17:12", "note": " "}, {"t": "17:24", "note": " "}, {"t": "17:33", "note": "右京の里経由です。"}, {"t": "17:51", "note": " "}, {"t": "18:00", "note": " "}, {"t": "18:09", "note": " "}, {"t": "18:18", "note": "右京の里経由です。"}, {"t": "18:28", "note": " "}, {"t": "18:38", "note": " "}, {"t": "18:48", "note": " "}, {"t": "18:58", "note": " "}, {"t": "19:07", "note": "右京の里経由です。"}, {"t": "19:26", "note": " "}, {"t": "19:36", "note": " "}, {"t": "19:46", "note": " "}, {"t": "19:56", "note": " "}, {"t": "20:06", "note": "右京の里経由です。"}, {"t": "20:16", "note": " "}, {"t": "20:26", "note": " "}, {"t": "20:37", "note": " "}, {"t": "21:01", "note": " "}, {"t": "21:13", "note": " "}, {"t": "21:25", "note": "右京の里経由です。"}, {"t": "21:37", "note": " "}, {"t": "21:49", "note": " "}, {"t": "22:14", "note": " "}], "saturday": [{"t": "06:34", "note": " "}, {"t": "06:53", "note": " "}, {"t": "07:12", "note": " "}, {"t": "07:25", "note": " "}, {"t": "07:38", "note": " "}, {"t": "07:50", "note": " "}, {"t": "08:01", "note": " "}, {"t": "08:12", "note": " "}, {"t": "08:23", "note": " "}, {"t": "08:35", "note": " "}, {"t": "08:48", "note": " "}, {"t": "09:00", "note": " "}, {"t": "09:24", "note": " "}, {"t": "09:36", "note": " "}, {"t": "09:48", "note": " "}, {"t": "10:00", "note": "右京の里経由です。"}, {"t": "10:12", "note": " "}, {"t": "10:24", "note": " "}, {"t": "10:48", "note": " "}, {"t": "11:00", "note": " "}, {"t": "11:12", "note": " "}, {"t": "11:24", "note": "右京の里経由です。"}, {"t": "11:36", "note": " "}, {"t": "11:48", "note": " "}, {"t": "12:12", "note": " "}, {"t": "12:24", "note": " "}, {"t": "12:36", "note": " "}, {"t": "12:48", "note": "右京の里経由です。"}, {"t": "13:00", "note": " "}, {"t": "13:12", "note": " "}, {"t": "13:36", "note": " "}, {"t": "13:48", "note": " "}, {"t": "14:00", "note": " "}, {"t": "14:12", "note": "右京の里経由です。"}, {"t": "14:24", "note": " "}, {"t": "14:36", "note": " "}, {"t": "15:00", "note": " "}, {"t": "15:12", "note": " "}, {"t": "15:24", "note": " "}, {"t": "15:36", "note": "右京の里経由です。"}, {"t": "15:48", "note": " "}, {"t": "16:00", "note": " "}, {"t": "16:24", "note": " "}, {"t": "16:36", "note": "右京の里経由です。"}, {"t": "16:48", "note": " "}, {"t": "17:00", "note": " "}, {"t": "17:12", "note": " "}, {"t": "17:24", "note": " "}, {"t": "17:36", "note": "右京の里経由です。"}, {"t": "17:48", "note": " "}, {"t": "18:02", "note": " "}, {"t": "18:31", "note": "右京の里経由です。"}, {"t": "18:46", "note": " "}, {"t": "19:01", "note": " "}, {"t": "19:14", "note": " "}, {"t": "19:29", "note": "右京の里経由です。"}, {"t": "19:44", "note": " "}, {"t": "19:59", "note": "右京の里経由です。"}, {"t": "20:29", "note": " "}, {"t": "20:44", "note": " "}, {"t": "20:59", "note": " "}, {"t": "21:14", "note": "右京の里経由です。"}, {"t": "21:29", "note": " "}, {"t": "21:49", "note": " "}, {"t": "22:14", "note": " "}], "holiday": [{"t": "07:11", "note": " "}, {"t": "07:28", "note": " "}, {"t": "07:46", "note": " "}, {"t": "08:04", "note": " "}, {"t": "08:22", "note": " "}, {"t": "08:38", "note": " "}, {"t": "08:54", "note": " "}, {"t": "09:09", "note": " "}, {"t": "09:39", "note": " "}, {"t": "09:54", "note": "右京の里経由です。"}, {"t": "10:09", "note": " "}, {"t": "10:24", "note": " "}, {"t": "10:48", "note": " "}, {"t": "11:00", "note": " "}, {"t": "11:12", "note": " "}, {"t": "11:24", "note": "右京の里経由です。"}, {"t": "11:36", "note": " "}, {"t": "11:48", "note": " "}, {"t": "12:12", "note": " "}, {"t": "12:24", "note": " "}, {"t": "12:36", "note": " "}, {"t": "12:48", "note": "右京の里経由です。"}, {"t": "13:00", "note": " "}, {"t": "13:12", "note": " "}, {"t": "13:36", "note": " "}, {"t": "13:48", "note": " "}, {"t": "14:00", "note": " "}, {"t": "14:12", "note": "右京の里経由です。"}, {"t": "14:24", "note": " "}, {"t": "14:36", "note": " "}, {"t": "15:00", "note": " "}, {"t": "15:12", "note": " "}, {"t": "15:24", "note": " "}, {"t": "15:36", "note": "右京の里経由です。"}, {"t": "15:48", "note": " "}, {"t": "16:00", "note": " "}, {"t": "16:24", "note": " "}, {"t": "16:36", "note": "右京の里経由です。"}, {"t": "16:48", "note": " "}, {"t": "17:00", "note": " "}, {"t": "17:12", "note": " "}, {"t": "17:26", "note": " "}, {"t": "17:41", "note": "右京の里経由です。"}, {"t": "17:56", "note": " "}, {"t": "18:26", "note": " "}, {"t": "18:41", "note": "右京の里経由です。"}, {"t": "18:56", "note": " "}, {"t": "19:10", "note": " "}, {"t": "19:29", "note": " "}, {"t": "19:49", "note": "右京の里経由です。"}, {"t": "20:29", "note": " "}, {"t": "20:49", "note": " "}, {"t": "21:09", "note": "右京の里経由です。"}, {"t": "21:29", "note": " "}, {"t": "21:49", "note": " "}, {"t": "22:14", "note": " "}]}